{
    "total_tvl": "10.4M",
    "total_volume_24h": "808.5K",
    "total_projects": 16,
    "networks_split": "16 / 0 (Kasplex)",
    "projects": [
        {
            "name": "Nacho the Kat",
            "symbol": "NACHO",
            "price": 1.96e-05,
            "tvl": 5630620,
            "volume_24h": 82229,
            "change_24h": -1.71218,
            "category": "KRC-20",
            "network": "Kasplex",
            "visit": "https://www.coingecko.com/en/coins/nacho-the-kat"
        },
        {
            "name": "Kaspy",
            "symbol": "KASPY",
            "price": 3.73e-06,
            "tvl": 1234393,
            "volume_24h": 33627,
            "change_24h": -1.48439,
            "category": "KRC-20",
            "network": "Kasplex",
            "visit": "https://www.coingecko.com/en/coins/kaspy"
        },
        {
            "name": "KANGO",
            "symbol": "KANGO",
            "price": 4.18e-06,
            "tvl": 1211948,
            "volume_24h": 221701,
            "change_24h": 19.67844,
            "category": "KRC-20",
            "network": "Kasplex",
            "visit": "https://www.coingecko.com/en/coins/kango"
        },
        {
            "name": "Kasper",
            "symbol": "KASPER",
            "price": 2.079e-05,
            "tvl": 596679,
            "volume_24h": 55863,
            "change_24h": -1.98125,
            "category": "KRC-20",
            "network": "Kasplex",
            "visit": "https://www.coingecko.com/en/coins/kasper"
        },
        {
            "name": "ZEAL",
            "symbol": "ZEAL",
            "price": 0.01135179,
            "tvl": 581012,
            "volume_24h": 39499,
            "change_24h": -2.38295,
            "category": "KRC-20",
            "network": "Kasplex",
            "visit": "https://www.coingecko.com/en/coins/zeal"
        },
        {
            "name": "PPKAS",
            "symbol": "PPKAS",
            "price": 0.00029382,
            "tvl": 282778,
            "volume_24h": 48741,
            "change_24h": -4.04577,
            "category": "KRC-20",
            "network": "Kasplex",
            "visit": "https://www.coingecko.com/en/coins/ppkas"
        },
        {
            "name": "Konan of Kaspa",
            "symbol": "KONAN",
            "price": 8.69053e-07,
            "tvl": 248667,
            "volume_24h": 56841,
            "change_24h": -0.01861,
            "category": "KRC-20",
            "network": "Kasplex",
            "visit": "https://www.coingecko.com/en/coins/konan-of-kaspa"
        },
        {
            "name": "Bitcoin the Turtle",
            "symbol": "SLOW",
            "price": 0.00751022,
            "tvl": 151578,
            "volume_24h": 52307,
            "change_24h": -3.57219,
            "category": "KRC-20",
            "network": "Kasplex",
            "visit": "https://www.coingecko.com/en/coins/bitcoin-the-turtle"
        },
        {
            "name": "Krex",
            "symbol": "KREX",
            "price": 6.52e-06,
            "tvl": 137527,
            "volume_24h": 34426,
            "change_24h": -0.59383,
            "category": "KRC-20",
            "network": "Kasplex",
            "visit": "https://www.coingecko.com/en/coins/krex"
        },
        {
            "name": "Keke",
            "symbol": "KEKE",
            "price": 1.63104e-07,
            "tvl": 112542,
            "volume_24h": 3355.11,
            "change_24h": -1.96133,
            "category": "KRC-20",
            "network": "Kasplex",
            "visit": "https://www.coingecko.com/en/coins/keke"
        },
        {
            "name": "GHOAD",
            "symbol": "GHOAD",
            "price": 1.878e-05,
            "tvl": 75110,
            "volume_24h": 3296.75,
            "change_24h": -6.45871,
            "category": "KRC-20",
            "network": "Kasplex",
            "visit": "https://www.coingecko.com/en/coins/ghoad"
        },
        {
            "name": "Burt",
            "symbol": "BURT",
            "price": 5.883e-05,
            "tvl": 58830,
            "volume_24h": 19218.59,
            "change_24h": -1.27913,
            "category": "KRC-20",
            "network": "Kasplex",
            "visit": "https://www.coingecko.com/en/coins/burt"
        },
        {
            "name": "Kroak on Kaspa",
            "symbol": "KROAK",
            "price": 7.4e-05,
            "tvl": 50851,
            "volume_24h": 25976,
            "change_24h": -10.71354,
            "category": "KRC-20",
            "network": "Kasplex",
            "visit": "https://www.coingecko.com/en/coins/kroak-on-kaspa"
        },
        {
            "name": "BOMO",
            "symbol": "BOMO",
            "price": 4.2944e-08,
            "tvl": 12024.35,
            "volume_24h": 78900,
            "change_24h": -2.38025,
            "category": "KRC-20",
            "network": "Kasplex",
            "visit": "https://www.coingecko.com/en/coins/bomo"
        },
        {
            "name": "SZAR",
            "symbol": "SZAR",
            "price": 6.6913e-08,
            "tvl": 6239.25,
            "volume_24h": 52559,
            "change_24h": -0.11002,
            "category": "KRC-20",
            "network": "Kasplex",
            "visit": "https://www.coingecko.com/en/coins/szar"
        },
        {
            "name": "Froppy",
            "symbol": "FROPPY",
            "price": 5.998e-09,
            "tvl": 1721.39,
            "volume_24h": 7.25,
            "change_24h": 0,
            "category": "KRC-20",
            "network": "Kasplex",
            "visit": "https://www.coingecko.com/en/coins/froppy"
        }
    ]
}