{
    "total_tvl": "7.9M",
    "total_volume_24h": "905.3K",
    "total_projects": 16,
    "networks_split": "16 / 0 (Kasplex)",
    "projects": [
        {
            "name": "Nacho the Kat",
            "symbol": "NACHO",
            "price": 1.453e-05,
            "tvl": 4153717,
            "volume_24h": 80320,
            "change_24h": -1.18986,
            "category": "KRC-20",
            "network": "Kasplex",
            "visit": "https://www.coingecko.com/en/coins/nacho-the-kat"
        },
        {
            "name": "Kaspy",
            "symbol": "KASPY",
            "price": 2.93e-06,
            "tvl": 968916,
            "volume_24h": 24815,
            "change_24h": -4.05865,
            "category": "KRC-20",
            "network": "Kasplex",
            "visit": "https://www.coingecko.com/en/coins/kaspy"
        },
        {
            "name": "KANGO",
            "symbol": "KANGO",
            "price": 2.18e-06,
            "tvl": 627001,
            "volume_24h": 156505,
            "change_24h": 19.53289,
            "category": "KRC-20",
            "network": "Kasplex",
            "visit": "https://www.coingecko.com/en/coins/kango"
        },
        {
            "name": "ZEAL",
            "symbol": "ZEAL",
            "price": 0.01089717,
            "tvl": 557418,
            "volume_24h": 180442,
            "change_24h": -0.40843,
            "category": "KRC-20",
            "network": "Kasplex",
            "visit": "https://www.coingecko.com/en/coins/zeal"
        },
        {
            "name": "Kasper",
            "symbol": "KASPER",
            "price": 1.817e-05,
            "tvl": 521555,
            "volume_24h": 57953,
            "change_24h": 2.66456,
            "category": "KRC-20",
            "network": "Kasplex",
            "visit": "https://www.coingecko.com/en/coins/kasper"
        },
        {
            "name": "PPKAS",
            "symbol": "PPKAS",
            "price": 0.00029597,
            "tvl": 284925,
            "volume_24h": 48778,
            "change_24h": 1.00556,
            "category": "KRC-20",
            "network": "Kasplex",
            "visit": "https://www.coingecko.com/en/coins/ppkas"
        },
        {
            "name": "Konan of Kaspa",
            "symbol": "KONAN",
            "price": 8.29193e-07,
            "tvl": 237978,
            "volume_24h": 64952,
            "change_24h": 5.34361,
            "category": "KRC-20",
            "network": "Kasplex",
            "visit": "https://www.coingecko.com/en/coins/konan-of-kaspa"
        },
        {
            "name": "Bitcoin the Turtle",
            "symbol": "SLOW",
            "price": 0.00831917,
            "tvl": 198823,
            "volume_24h": 46177,
            "change_24h": -15.34553,
            "category": "KRC-20",
            "network": "Kasplex",
            "visit": "https://www.coingecko.com/en/coins/bitcoin-the-turtle"
        },
        {
            "name": "Keke",
            "symbol": "KEKE",
            "price": 1.51104e-07,
            "tvl": 104262,
            "volume_24h": 3950.95,
            "change_24h": -2.1706,
            "category": "KRC-20",
            "network": "Kasplex",
            "visit": "https://www.coingecko.com/en/coins/keke"
        },
        {
            "name": "GHOAD",
            "symbol": "GHOAD",
            "price": 2.488e-05,
            "tvl": 99511,
            "volume_24h": 2799.23,
            "change_24h": -0.57092,
            "category": "KRC-20",
            "network": "Kasplex",
            "visit": "https://www.coingecko.com/en/coins/ghoad"
        },
        {
            "name": "Burt",
            "symbol": "BURT",
            "price": 6.515e-05,
            "tvl": 65151,
            "volume_24h": 48970,
            "change_24h": -3.5955,
            "category": "KRC-20",
            "network": "Kasplex",
            "visit": "https://www.coingecko.com/en/coins/burt"
        },
        {
            "name": "Krex",
            "symbol": "KREX",
            "price": 2.65e-06,
            "tvl": 55606,
            "volume_24h": 29161,
            "change_24h": 2.3155,
            "category": "KRC-20",
            "network": "Kasplex",
            "visit": "https://www.coingecko.com/en/coins/krex"
        },
        {
            "name": "Kroak on Kaspa",
            "symbol": "KROAK",
            "price": 6.721e-05,
            "tvl": 46377,
            "volume_24h": 25748,
            "change_24h": -9.90629,
            "category": "KRC-20",
            "network": "Kasplex",
            "visit": "https://www.coingecko.com/en/coins/kroak-on-kaspa"
        },
        {
            "name": "BOMO",
            "symbol": "BOMO",
            "price": 5.1932e-08,
            "tvl": 14260.01,
            "volume_24h": 81018,
            "change_24h": -0.01001,
            "category": "KRC-20",
            "network": "Kasplex",
            "visit": "https://www.coingecko.com/en/coins/bomo"
        },
        {
            "name": "SZAR",
            "symbol": "SZAR",
            "price": 6.6913e-08,
            "tvl": 5888.34,
            "volume_24h": 53674,
            "change_24h": 1.51515,
            "category": "KRC-20",
            "network": "Kasplex",
            "visit": "https://www.coingecko.com/en/coins/szar"
        },
        {
            "name": "Froppy",
            "symbol": "FROPPY",
            "price": 7e-09,
            "tvl": 2009.01,
            "volume_24h": 6.8,
            "change_24h": 0,
            "category": "KRC-20",
            "network": "Kasplex",
            "visit": "https://www.coingecko.com/en/coins/froppy"
        }
    ]
}