{
    "total_tvl": "7.9M",
    "total_volume_24h": "826.5K",
    "total_projects": 17,
    "networks_split": "17 / 0 (Kasplex)",
    "projects": [
        {
            "name": "Nacho the Kat",
            "symbol": "NACHO",
            "price": 1.408e-05,
            "tvl": 4031936,
            "volume_24h": 121565,
            "change_24h": -1.06014,
            "category": "KRC-20",
            "network": "Kasplex",
            "visit": "https://www.coingecko.com/en/coins/nacho-the-kat"
        },
        {
            "name": "Kaspy",
            "symbol": "KASPY",
            "price": 2.7e-06,
            "tvl": 897835,
            "volume_24h": 23233,
            "change_24h": 2.35564,
            "category": "KRC-20",
            "network": "Kasplex",
            "visit": "https://www.coingecko.com/en/coins/kaspy"
        },
        {
            "name": "KANGO",
            "symbol": "KANGO",
            "price": 2.42e-06,
            "tvl": 695001,
            "volume_24h": 184862,
            "change_24h": 34.96138,
            "category": "KRC-20",
            "network": "Kasplex",
            "visit": "https://www.coingecko.com/en/coins/kango"
        },
        {
            "name": "ZEAL",
            "symbol": "ZEAL",
            "price": 0.01197282,
            "tvl": 611811,
            "volume_24h": 47466,
            "change_24h": 0.52529,
            "category": "KRC-20",
            "network": "Kasplex",
            "visit": "https://www.coingecko.com/en/coins/zeal"
        },
        {
            "name": "Kasper",
            "symbol": "KASPER",
            "price": 2.066e-05,
            "tvl": 588015,
            "volume_24h": 68551,
            "change_24h": 11.65588,
            "category": "KRC-20",
            "network": "Kasplex",
            "visit": "https://www.coingecko.com/en/coins/kasper"
        },
        {
            "name": "PPKAS",
            "symbol": "PPKAS",
            "price": 0.00030183,
            "tvl": 291556,
            "volume_24h": 53343,
            "change_24h": -5.54486,
            "category": "KRC-20",
            "network": "Kasplex",
            "visit": "https://www.coingecko.com/en/coins/ppkas"
        },
        {
            "name": "Konan of Kaspa",
            "symbol": "KONAN",
            "price": 8.70585e-07,
            "tvl": 249858,
            "volume_24h": 64023,
            "change_24h": 0.4538,
            "category": "KRC-20",
            "network": "Kasplex",
            "visit": "https://www.coingecko.com/en/coins/konan-of-kaspa"
        },
        {
            "name": "Bitcoin the Turtle",
            "symbol": "SLOW",
            "price": 0.00748775,
            "tvl": 147892,
            "volume_24h": 52582,
            "change_24h": 0.94163,
            "category": "KRC-20",
            "network": "Kasplex",
            "visit": "https://www.coingecko.com/en/coins/bitcoin-the-turtle"
        },
        {
            "name": "Keke",
            "symbol": "KEKE",
            "price": 1.46843e-07,
            "tvl": 101322,
            "volume_24h": 4694.74,
            "change_24h": -2.53096,
            "category": "KRC-20",
            "network": "Kasplex",
            "visit": "https://www.coingecko.com/en/coins/keke"
        },
        {
            "name": "GHOAD",
            "symbol": "GHOAD",
            "price": 2.05e-05,
            "tvl": 82008,
            "volume_24h": 2796.14,
            "change_24h": 3.83809,
            "category": "KRC-20",
            "network": "Kasplex",
            "visit": "https://www.coingecko.com/en/coins/ghoad"
        },
        {
            "name": "Burt",
            "symbol": "BURT",
            "price": 6.631e-05,
            "tvl": 66303,
            "volume_24h": 19716.16,
            "change_24h": -6.50553,
            "category": "KRC-20",
            "network": "Kasplex",
            "visit": "https://www.coingecko.com/en/coins/burt"
        },
        {
            "name": "Kroak on Kaspa",
            "symbol": "KROAK",
            "price": 9.067e-05,
            "tvl": 63154,
            "volume_24h": 23569,
            "change_24h": 2.50638,
            "category": "KRC-20",
            "network": "Kasplex",
            "visit": "https://www.coingecko.com/en/coins/kroak-on-kaspa"
        },
        {
            "name": "Krex",
            "symbol": "KREX",
            "price": 2.25e-06,
            "tvl": 46721,
            "volume_24h": 27914,
            "change_24h": 4.35499,
            "category": "KRC-20",
            "network": "Kasplex",
            "visit": "https://www.coingecko.com/en/coins/krex"
        },
        {
            "name": "BOMO",
            "symbol": "BOMO",
            "price": 5.3984e-08,
            "tvl": 15404.62,
            "volume_24h": 77608,
            "change_24h": 1.90718,
            "category": "KRC-20",
            "network": "Kasplex",
            "visit": "https://www.coingecko.com/en/coins/bomo"
        },
        {
            "name": "SZAR",
            "symbol": "SZAR",
            "price": 6.8979e-08,
            "tvl": 5897.77,
            "volume_24h": 54529,
            "change_24h": 2.98507,
            "category": "KRC-20",
            "network": "Kasplex",
            "visit": "https://www.coingecko.com/en/coins/szar"
        },
        {
            "name": "Froppy",
            "symbol": "FROPPY",
            "price": 7e-09,
            "tvl": 2009.01,
            "volume_24h": 6.8,
            "change_24h": 0,
            "category": "KRC-20",
            "network": "Kasplex",
            "visit": "https://www.coingecko.com/en/coins/froppy"
        },
        {
            "name": "Dagknight Dog",
            "symbol": "DOGK",
            "price": 6.99927e-07,
            "tvl": 1587.31,
            "volume_24h": 0.03499634,
            "change_24h": 0,
            "category": "KRC-20",
            "network": "Kasplex",
            "visit": "https://www.coingecko.com/en/coins/dogk"
        }
    ]
}