{
    "total_tvl": "8.2M",
    "total_volume_24h": "894.0K",
    "total_projects": 18,
    "networks_split": "18 / 0 (Kasplex)",
    "projects": [
        {
            "name": "Nacho the Kat",
            "symbol": "NACHO",
            "price": 1.474e-05,
            "tvl": 4233741,
            "volume_24h": 204543,
            "change_24h": 16.74406,
            "category": "KRC-20",
            "network": "Kasplex",
            "visit": "https://www.coingecko.com/en/coins/nacho-the-kat"
        },
        {
            "name": "Kaspy",
            "symbol": "KASPY",
            "price": 3.38e-06,
            "tvl": 1125006,
            "volume_24h": 24988,
            "change_24h": 2.85229,
            "category": "KRC-20",
            "network": "Kasplex",
            "visit": "https://www.coingecko.com/en/coins/kaspy"
        },
        {
            "name": "ZEAL",
            "symbol": "ZEAL",
            "price": 0.01291634,
            "tvl": 660025,
            "volume_24h": 50090,
            "change_24h": 1.58398,
            "category": "KRC-20",
            "network": "Kasplex",
            "visit": "https://www.coingecko.com/en/coins/zeal"
        },
        {
            "name": "Kasper",
            "symbol": "KASPER",
            "price": 1.74e-05,
            "tvl": 499283,
            "volume_24h": 56776,
            "change_24h": -4.18817,
            "category": "KRC-20",
            "network": "Kasplex",
            "visit": "https://www.coingecko.com/en/coins/kasper"
        },
        {
            "name": "KANGO",
            "symbol": "KANGO",
            "price": 1.72e-06,
            "tvl": 492101,
            "volume_24h": 107720,
            "change_24h": -17.20221,
            "category": "KRC-20",
            "network": "Kasplex",
            "visit": "https://www.coingecko.com/en/coins/kango"
        },
        {
            "name": "Konan of Kaspa",
            "symbol": "KONAN",
            "price": 1.03e-06,
            "tvl": 299013,
            "volume_24h": 68218,
            "change_24h": 23.21306,
            "category": "KRC-20",
            "network": "Kasplex",
            "visit": "https://www.coingecko.com/en/coins/konan-of-kaspa"
        },
        {
            "name": "PPKAS",
            "symbol": "PPKAS",
            "price": 0.0002958,
            "tvl": 290160,
            "volume_24h": 51725,
            "change_24h": -3.0656,
            "category": "KRC-20",
            "network": "Kasplex",
            "visit": "https://www.coingecko.com/en/coins/ppkas"
        },
        {
            "name": "Bitcoin the Turtle",
            "symbol": "SLOW",
            "price": 0.00941228,
            "tvl": 185545,
            "volume_24h": 81745,
            "change_24h": -0.49958,
            "category": "KRC-20",
            "network": "Kasplex",
            "visit": "https://www.coingecko.com/en/coins/bitcoin-the-turtle"
        },
        {
            "name": "Keke",
            "symbol": "KEKE",
            "price": 1.50456e-07,
            "tvl": 103819,
            "volume_24h": 5296.69,
            "change_24h": -16.81486,
            "category": "KRC-20",
            "network": "Kasplex",
            "visit": "https://www.coingecko.com/en/coins/keke"
        },
        {
            "name": "GHOAD",
            "symbol": "GHOAD",
            "price": 2.471e-05,
            "tvl": 98856,
            "volume_24h": 3183.08,
            "change_24h": 2.43384,
            "category": "KRC-20",
            "network": "Kasplex",
            "visit": "https://www.coingecko.com/en/coins/ghoad"
        },
        {
            "name": "Burt",
            "symbol": "BURT",
            "price": 8.817e-05,
            "tvl": 84048,
            "volume_24h": 55133,
            "change_24h": 57.58377,
            "category": "KRC-20",
            "network": "Kasplex",
            "visit": "https://www.coingecko.com/en/coins/burt"
        },
        {
            "name": "Kroak on Kaspa",
            "symbol": "KROAK",
            "price": 0.00010525,
            "tvl": 73387,
            "volume_24h": 24980,
            "change_24h": -0.5323,
            "category": "KRC-20",
            "network": "Kasplex",
            "visit": "https://www.coingecko.com/en/coins/kroak-on-kaspa"
        },
        {
            "name": "Krex",
            "symbol": "KREX",
            "price": 2.14e-06,
            "tvl": 46477,
            "volume_24h": 29581,
            "change_24h": -3.75744,
            "category": "KRC-20",
            "network": "Kasplex",
            "visit": "https://www.coingecko.com/en/coins/krex"
        },
        {
            "name": "BOMO",
            "symbol": "BOMO",
            "price": 5.2974e-08,
            "tvl": 14002.8,
            "volume_24h": 79316,
            "change_24h": -8.67551,
            "category": "KRC-20",
            "network": "Kasplex",
            "visit": "https://www.coingecko.com/en/coins/bomo"
        },
        {
            "name": "Kyro",
            "symbol": "KYRO",
            "price": 1.189e-05,
            "tvl": 11891.37,
            "volume_24h": 29.74,
            "change_24h": 0,
            "category": "KRC-20",
            "network": "Kasplex",
            "visit": "https://www.coingecko.com/en/coins/kyro"
        },
        {
            "name": "SZAR",
            "symbol": "SZAR",
            "price": 6.4968e-08,
            "tvl": 5717.14,
            "volume_24h": 50626,
            "change_24h": -0.05999,
            "category": "KRC-20",
            "network": "Kasplex",
            "visit": "https://www.coingecko.com/en/coins/szar"
        },
        {
            "name": "Froppy",
            "symbol": "FROPPY",
            "price": 7e-09,
            "tvl": 2009.01,
            "volume_24h": 6.8,
            "change_24h": 0,
            "category": "KRC-20",
            "network": "Kasplex",
            "visit": "https://www.coingecko.com/en/coins/froppy"
        },
        {
            "name": "Dagknight Dog",
            "symbol": "DOGK",
            "price": 6.99927e-07,
            "tvl": 1587.31,
            "volume_24h": 0.03499634,
            "change_24h": 0,
            "category": "KRC-20",
            "network": "Kasplex",
            "visit": "https://www.coingecko.com/en/coins/dogk"
        }
    ]
}