{
    "total_tvl": "10.1M",
    "total_volume_24h": "750.4K",
    "total_projects": 16,
    "networks_split": "16 / 0 (Kasplex)",
    "projects": [
        {
            "name": "Nacho the Kat",
            "symbol": "NACHO",
            "price": 1.873e-05,
            "tvl": 5385086,
            "volume_24h": 89226,
            "change_24h": -1.66325,
            "category": "KRC-20",
            "network": "Kasplex",
            "visit": "https://www.coingecko.com/en/coins/nacho-the-kat"
        },
        {
            "name": "Kaspy",
            "symbol": "KASPY",
            "price": 3.8e-06,
            "tvl": 1256820,
            "volume_24h": 33239,
            "change_24h": 4.16649,
            "category": "KRC-20",
            "network": "Kasplex",
            "visit": "https://www.coingecko.com/en/coins/kaspy"
        },
        {
            "name": "KANGO",
            "symbol": "KANGO",
            "price": 3.66e-06,
            "tvl": 1051041,
            "volume_24h": 150575,
            "change_24h": 9.84965,
            "category": "KRC-20",
            "network": "Kasplex",
            "visit": "https://www.coingecko.com/en/coins/kango"
        },
        {
            "name": "Kasper",
            "symbol": "KASPER",
            "price": 2.255e-05,
            "tvl": 649812,
            "volume_24h": 60951,
            "change_24h": 8.78472,
            "category": "KRC-20",
            "network": "Kasplex",
            "visit": "https://www.coingecko.com/en/coins/kasper"
        },
        {
            "name": "ZEAL",
            "symbol": "ZEAL",
            "price": 0.01098189,
            "tvl": 561175,
            "volume_24h": 35955,
            "change_24h": 2.48239,
            "category": "KRC-20",
            "network": "Kasplex",
            "visit": "https://www.coingecko.com/en/coins/zeal"
        },
        {
            "name": "Konan of Kaspa",
            "symbol": "KONAN",
            "price": 9.04455e-07,
            "tvl": 256635,
            "volume_24h": 63193,
            "change_24h": -0.21992,
            "category": "KRC-20",
            "network": "Kasplex",
            "visit": "https://www.coingecko.com/en/coins/konan-of-kaspa"
        },
        {
            "name": "PPKAS",
            "symbol": "PPKAS",
            "price": 0.00026453,
            "tvl": 255783,
            "volume_24h": 43710,
            "change_24h": -2.53593,
            "category": "KRC-20",
            "network": "Kasplex",
            "visit": "https://www.coingecko.com/en/coins/ppkas"
        },
        {
            "name": "Krex",
            "symbol": "KREX",
            "price": 9.06e-06,
            "tvl": 190529,
            "volume_24h": 38477,
            "change_24h": 15.81229,
            "category": "KRC-20",
            "network": "Kasplex",
            "visit": "https://www.coingecko.com/en/coins/krex"
        },
        {
            "name": "Bitcoin the Turtle",
            "symbol": "SLOW",
            "price": 0.00710289,
            "tvl": 141187,
            "volume_24h": 55428,
            "change_24h": -7.19874,
            "category": "KRC-20",
            "network": "Kasplex",
            "visit": "https://www.coingecko.com/en/coins/bitcoin-the-turtle"
        },
        {
            "name": "Keke",
            "symbol": "KEKE",
            "price": 1.65884e-07,
            "tvl": 114460,
            "volume_24h": 2956.9,
            "change_24h": -1.1281,
            "category": "KRC-20",
            "network": "Kasplex",
            "visit": "https://www.coingecko.com/en/coins/keke"
        },
        {
            "name": "GHOAD",
            "symbol": "GHOAD",
            "price": 2.025e-05,
            "tvl": 81014,
            "volume_24h": 3570.08,
            "change_24h": 2.37549,
            "category": "KRC-20",
            "network": "Kasplex",
            "visit": "https://www.coingecko.com/en/coins/ghoad"
        },
        {
            "name": "Burt",
            "symbol": "BURT",
            "price": 5.689e-05,
            "tvl": 56894,
            "volume_24h": 17026.7,
            "change_24h": 0.43708,
            "category": "KRC-20",
            "network": "Kasplex",
            "visit": "https://www.coingecko.com/en/coins/burt"
        },
        {
            "name": "Kroak on Kaspa",
            "symbol": "KROAK",
            "price": 8.032e-05,
            "tvl": 54864,
            "volume_24h": 24978,
            "change_24h": 3.98953,
            "category": "KRC-20",
            "network": "Kasplex",
            "visit": "https://www.coingecko.com/en/coins/kroak-on-kaspa"
        },
        {
            "name": "BOMO",
            "symbol": "BOMO",
            "price": 4.3956e-08,
            "tvl": 12307.68,
            "volume_24h": 82882,
            "change_24h": 2.3051,
            "category": "KRC-20",
            "network": "Kasplex",
            "visit": "https://www.coingecko.com/en/coins/bomo"
        },
        {
            "name": "SZAR",
            "symbol": "SZAR",
            "price": 6.8931e-08,
            "tvl": 6065.93,
            "volume_24h": 48238,
            "change_24h": 4.52453,
            "category": "KRC-20",
            "network": "Kasplex",
            "visit": "https://www.coingecko.com/en/coins/szar"
        },
        {
            "name": "Froppy",
            "symbol": "FROPPY",
            "price": 5.998e-09,
            "tvl": 1721.39,
            "volume_24h": 7.25,
            "change_24h": 0,
            "category": "KRC-20",
            "network": "Kasplex",
            "visit": "https://www.coingecko.com/en/coins/froppy"
        }
    ]
}