{
    "total_tvl": "7.4M",
    "total_volume_24h": "813.6K",
    "total_projects": 18,
    "networks_split": "18 / 0 (Kasplex)",
    "projects": [
        {
            "name": "Nacho the Kat",
            "symbol": "NACHO",
            "price": 1.314e-05,
            "tvl": 3776071,
            "volume_24h": 116794,
            "change_24h": 0.09252,
            "category": "KRC-20",
            "network": "Kasplex",
            "visit": "https://www.coingecko.com/en/coins/nacho-the-kat"
        },
        {
            "name": "Kaspy",
            "symbol": "KASPY",
            "price": 2.66e-06,
            "tvl": 881538,
            "volume_24h": 26446,
            "change_24h": -16.28614,
            "category": "KRC-20",
            "network": "Kasplex",
            "visit": "https://www.coingecko.com/en/coins/kaspy"
        },
        {
            "name": "ZEAL",
            "symbol": "ZEAL",
            "price": 0.01189883,
            "tvl": 608017,
            "volume_24h": 55730,
            "change_24h": -5.01317,
            "category": "KRC-20",
            "network": "Kasplex",
            "visit": "https://www.coingecko.com/en/coins/zeal"
        },
        {
            "name": "Kasper",
            "symbol": "KASPER",
            "price": 1.745e-05,
            "tvl": 503423,
            "volume_24h": 58095,
            "change_24h": -1.36331,
            "category": "KRC-20",
            "network": "Kasplex",
            "visit": "https://www.coingecko.com/en/coins/kasper"
        },
        {
            "name": "KANGO",
            "symbol": "KANGO",
            "price": 1.61e-06,
            "tvl": 466059,
            "volume_24h": 129566,
            "change_24h": 7.36353,
            "category": "KRC-20",
            "network": "Kasplex",
            "visit": "https://www.coingecko.com/en/coins/kango"
        },
        {
            "name": "PPKAS",
            "symbol": "PPKAS",
            "price": 0.00031243,
            "tvl": 300771,
            "volume_24h": 54414,
            "change_24h": 4.04413,
            "category": "KRC-20",
            "network": "Kasplex",
            "visit": "https://www.coingecko.com/en/coins/ppkas"
        },
        {
            "name": "Konan of Kaspa",
            "symbol": "KONAN",
            "price": 8.52436e-07,
            "tvl": 240966,
            "volume_24h": 57428,
            "change_24h": -9.80771,
            "category": "KRC-20",
            "network": "Kasplex",
            "visit": "https://www.coingecko.com/en/coins/konan-of-kaspa"
        },
        {
            "name": "Bitcoin the Turtle",
            "symbol": "SLOW",
            "price": 0.00869109,
            "tvl": 171815,
            "volume_24h": 63830,
            "change_24h": 0.34075,
            "category": "KRC-20",
            "network": "Kasplex",
            "visit": "https://www.coingecko.com/en/coins/bitcoin-the-turtle"
        },
        {
            "name": "Keke",
            "symbol": "KEKE",
            "price": 1.63308e-07,
            "tvl": 111859,
            "volume_24h": 3255.68,
            "change_24h": 8.62674,
            "category": "KRC-20",
            "network": "Kasplex",
            "visit": "https://www.coingecko.com/en/coins/keke"
        },
        {
            "name": "Burt",
            "symbol": "BURT",
            "price": 9.381e-05,
            "tvl": 97769,
            "volume_24h": 56999,
            "change_24h": 46.02125,
            "category": "KRC-20",
            "network": "Kasplex",
            "visit": "https://www.coingecko.com/en/coins/burt"
        },
        {
            "name": "GHOAD",
            "symbol": "GHOAD",
            "price": 1.945e-05,
            "tvl": 76800,
            "volume_24h": 4357.5,
            "change_24h": -19.66566,
            "category": "KRC-20",
            "network": "Kasplex",
            "visit": "https://www.coingecko.com/en/coins/ghoad"
        },
        {
            "name": "Kroak on Kaspa",
            "symbol": "KROAK",
            "price": 9.072e-05,
            "tvl": 63707,
            "volume_24h": 23872,
            "change_24h": -12.65893,
            "category": "KRC-20",
            "network": "Kasplex",
            "visit": "https://www.coingecko.com/en/coins/kroak-on-kaspa"
        },
        {
            "name": "Krex",
            "symbol": "KREX",
            "price": 1.91e-06,
            "tvl": 40478,
            "volume_24h": 28119,
            "change_24h": -11.99504,
            "category": "KRC-20",
            "network": "Kasplex",
            "visit": "https://www.coingecko.com/en/coins/krex"
        },
        {
            "name": "BOMO",
            "symbol": "BOMO",
            "price": 5.5006e-08,
            "tvl": 15107.9,
            "volume_24h": 83106,
            "change_24h": 3.80472,
            "category": "KRC-20",
            "network": "Kasplex",
            "visit": "https://www.coingecko.com/en/coins/bomo"
        },
        {
            "name": "Kyro",
            "symbol": "KYRO",
            "price": 1.189e-05,
            "tvl": 11891.37,
            "volume_24h": 29.74,
            "change_24h": 0,
            "category": "KRC-20",
            "network": "Kasplex",
            "visit": "https://www.coingecko.com/en/coins/kyro"
        },
        {
            "name": "SZAR",
            "symbol": "SZAR",
            "price": 6.5007e-08,
            "tvl": 5895.41,
            "volume_24h": 51529,
            "change_24h": -4.38308,
            "category": "KRC-20",
            "network": "Kasplex",
            "visit": "https://www.coingecko.com/en/coins/szar"
        },
        {
            "name": "Froppy",
            "symbol": "FROPPY",
            "price": 7e-09,
            "tvl": 2009.01,
            "volume_24h": 6.8,
            "change_24h": 0,
            "category": "KRC-20",
            "network": "Kasplex",
            "visit": "https://www.coingecko.com/en/coins/froppy"
        },
        {
            "name": "Dagknight Dog",
            "symbol": "DOGK",
            "price": 6.99927e-07,
            "tvl": 1587.31,
            "volume_24h": 0.03499634,
            "change_24h": 0,
            "category": "KRC-20",
            "network": "Kasplex",
            "visit": "https://www.coingecko.com/en/coins/dogk"
        }
    ]
}