{
    "total_tvl": "6.5M",
    "total_volume_24h": "647.8K",
    "total_projects": 16,
    "networks_split": "16 / 0 (Kasplex)",
    "projects": [
        {
            "name": "Nacho the Kat",
            "symbol": "NACHO",
            "price": 1.128e-05,
            "tvl": 3227527,
            "volume_24h": 79826,
            "change_24h": -3.50334,
            "category": "KRC-20",
            "network": "Kasplex",
            "visit": "https://www.coingecko.com/en/coins/nacho-the-kat"
        },
        {
            "name": "Kaspy",
            "symbol": "KASPY",
            "price": 3.22e-06,
            "tvl": 1068427,
            "volume_24h": 18026.22,
            "change_24h": -3.22199,
            "category": "KRC-20",
            "network": "Kasplex",
            "visit": "https://www.coingecko.com/en/coins/kaspy"
        },
        {
            "name": "KANGO",
            "symbol": "KANGO",
            "price": 1.86e-06,
            "tvl": 534990,
            "volume_24h": 67737,
            "change_24h": -6.02096,
            "category": "KRC-20",
            "network": "Kasplex",
            "visit": "https://www.coingecko.com/en/coins/kango"
        },
        {
            "name": "Kasper",
            "symbol": "KASPER",
            "price": 1.426e-05,
            "tvl": 403749,
            "volume_24h": 62102,
            "change_24h": 1.27281,
            "category": "KRC-20",
            "network": "Kasplex",
            "visit": "https://www.coingecko.com/en/coins/kasper"
        },
        {
            "name": "ZEAL",
            "symbol": "ZEAL",
            "price": 0.00676263,
            "tvl": 345571,
            "volume_24h": 6177.55,
            "change_24h": 0.32573,
            "category": "KRC-20",
            "network": "Kasplex",
            "visit": "https://www.coingecko.com/en/coins/zeal"
        },
        {
            "name": "PPKAS",
            "symbol": "PPKAS",
            "price": 0.00026797,
            "tvl": 257969,
            "volume_24h": 44256,
            "change_24h": -1.8094,
            "category": "KRC-20",
            "network": "Kasplex",
            "visit": "https://www.coingecko.com/en/coins/ppkas"
        },
        {
            "name": "Konan of Kaspa",
            "symbol": "KONAN",
            "price": 5.78371e-07,
            "tvl": 165993,
            "volume_24h": 59031,
            "change_24h": 0.23722,
            "category": "KRC-20",
            "network": "Kasplex",
            "visit": "https://www.coingecko.com/en/coins/konan-of-kaspa"
        },
        {
            "name": "GHOAD",
            "symbol": "GHOAD",
            "price": 3.196e-05,
            "tvl": 127856,
            "volume_24h": 4458.68,
            "change_24h": 0,
            "category": "KRC-20",
            "network": "Kasplex",
            "visit": "https://www.coingecko.com/en/coins/ghoad"
        },
        {
            "name": "Keke",
            "symbol": "KEKE",
            "price": 1.46435e-07,
            "tvl": 101040,
            "volume_24h": 3008.19,
            "change_24h": 0,
            "category": "KRC-20",
            "network": "Kasplex",
            "visit": "https://www.coingecko.com/en/coins/keke"
        },
        {
            "name": "Bitcoin the Turtle",
            "symbol": "SLOW",
            "price": 0.0051054,
            "tvl": 93937,
            "volume_24h": 60449,
            "change_24h": 6.93588,
            "category": "KRC-20",
            "network": "Kasplex",
            "visit": "https://www.coingecko.com/en/coins/bitcoin-the-turtle"
        },
        {
            "name": "Krex",
            "symbol": "KREX",
            "price": 3.71e-06,
            "tvl": 77917,
            "volume_24h": 37197,
            "change_24h": 1.82407,
            "category": "KRC-20",
            "network": "Kasplex",
            "visit": "https://www.coingecko.com/en/coins/krex"
        },
        {
            "name": "Kroak on Kaspa",
            "symbol": "KROAK",
            "price": 0.00010976,
            "tvl": 76282,
            "volume_24h": 53139,
            "change_24h": 15.28935,
            "category": "KRC-20",
            "network": "Kasplex",
            "visit": "https://www.coingecko.com/en/coins/kroak-on-kaspa"
        },
        {
            "name": "Burt",
            "symbol": "BURT",
            "price": 4.84e-05,
            "tvl": 48388,
            "volume_24h": 15227.35,
            "change_24h": -1.04835,
            "category": "KRC-20",
            "network": "Kasplex",
            "visit": "https://www.coingecko.com/en/coins/burt"
        },
        {
            "name": "BOMO",
            "symbol": "BOMO",
            "price": 4.2961e-08,
            "tvl": 12029.16,
            "volume_24h": 81005,
            "change_24h": 4.92005,
            "category": "KRC-20",
            "network": "Kasplex",
            "visit": "https://www.coingecko.com/en/coins/bomo"
        },
        {
            "name": "SZAR",
            "symbol": "SZAR",
            "price": 6.5941e-08,
            "tvl": 5802.77,
            "volume_24h": 56162,
            "change_24h": -2.9023,
            "category": "KRC-20",
            "network": "Kasplex",
            "visit": "https://www.coingecko.com/en/coins/szar"
        },
        {
            "name": "Froppy",
            "symbol": "FROPPY",
            "price": 5.993e-09,
            "tvl": 1720.11,
            "volume_24h": 9.95,
            "change_24h": 0,
            "category": "KRC-20",
            "network": "Kasplex",
            "visit": "https://www.coingecko.com/en/coins/froppy"
        }
    ]
}