{
    "total_tvl": "9.9M",
    "total_volume_24h": "760.2K",
    "total_projects": 16,
    "networks_split": "16 / 0 (Kasplex)",
    "projects": [
        {
            "name": "Nacho the Kat",
            "symbol": "NACHO",
            "price": 1.84e-05,
            "tvl": 5291777,
            "volume_24h": 79404,
            "change_24h": -3.62084,
            "category": "KRC-20",
            "network": "Kasplex",
            "visit": "https://www.coingecko.com/en/coins/nacho-the-kat"
        },
        {
            "name": "Kaspy",
            "symbol": "KASPY",
            "price": 3.66e-06,
            "tvl": 1210124,
            "volume_24h": 33917,
            "change_24h": -3.73955,
            "category": "KRC-20",
            "network": "Kasplex",
            "visit": "https://www.coingecko.com/en/coins/kaspy"
        },
        {
            "name": "KANGO",
            "symbol": "KANGO",
            "price": 3.72e-06,
            "tvl": 1073016,
            "volume_24h": 174821,
            "change_24h": -27.31835,
            "category": "KRC-20",
            "network": "Kasplex",
            "visit": "https://www.coingecko.com/en/coins/kango"
        },
        {
            "name": "Kasper",
            "symbol": "KASPER",
            "price": 2.079e-05,
            "tvl": 597159,
            "volume_24h": 55903,
            "change_24h": -0.31855,
            "category": "KRC-20",
            "network": "Kasplex",
            "visit": "https://www.coingecko.com/en/coins/kasper"
        },
        {
            "name": "ZEAL",
            "symbol": "ZEAL",
            "price": 0.01099025,
            "tvl": 561602,
            "volume_24h": 40565,
            "change_24h": -4.7305,
            "category": "KRC-20",
            "network": "Kasplex",
            "visit": "https://www.coingecko.com/en/coins/zeal"
        },
        {
            "name": "Konan of Kaspa",
            "symbol": "KONAN",
            "price": 9.06941e-07,
            "tvl": 260958,
            "volume_24h": 62365,
            "change_24h": 0.7392,
            "category": "KRC-20",
            "network": "Kasplex",
            "visit": "https://www.coingecko.com/en/coins/konan-of-kaspa"
        },
        {
            "name": "PPKAS",
            "symbol": "PPKAS",
            "price": 0.00025945,
            "tvl": 249908,
            "volume_24h": 43840,
            "change_24h": -10.40921,
            "category": "KRC-20",
            "network": "Kasplex",
            "visit": "https://www.coingecko.com/en/coins/ppkas"
        },
        {
            "name": "Krex",
            "symbol": "KREX",
            "price": 9.06e-06,
            "tvl": 189548,
            "volume_24h": 40995,
            "change_24h": 20.86286,
            "category": "KRC-20",
            "network": "Kasplex",
            "visit": "https://www.coingecko.com/en/coins/krex"
        },
        {
            "name": "Bitcoin the Turtle",
            "symbol": "SLOW",
            "price": 0.00715853,
            "tvl": 139851,
            "volume_24h": 53018,
            "change_24h": -5.54142,
            "category": "KRC-20",
            "network": "Kasplex",
            "visit": "https://www.coingecko.com/en/coins/bitcoin-the-turtle"
        },
        {
            "name": "Keke",
            "symbol": "KEKE",
            "price": 1.65875e-07,
            "tvl": 114454,
            "volume_24h": 2997.82,
            "change_24h": -1.16483,
            "category": "KRC-20",
            "network": "Kasplex",
            "visit": "https://www.coingecko.com/en/coins/keke"
        },
        {
            "name": "GHOAD",
            "symbol": "GHOAD",
            "price": 2.004e-05,
            "tvl": 80171,
            "volume_24h": 3537.69,
            "change_24h": 1.89499,
            "category": "KRC-20",
            "network": "Kasplex",
            "visit": "https://www.coingecko.com/en/coins/ghoad"
        },
        {
            "name": "Burt",
            "symbol": "BURT",
            "price": 5.689e-05,
            "tvl": 56894,
            "volume_24h": 18075.38,
            "change_24h": 0.96381,
            "category": "KRC-20",
            "network": "Kasplex",
            "visit": "https://www.coingecko.com/en/coins/burt"
        },
        {
            "name": "Kroak on Kaspa",
            "symbol": "KROAK",
            "price": 7.807e-05,
            "tvl": 55150,
            "volume_24h": 24658,
            "change_24h": 0.0679,
            "category": "KRC-20",
            "network": "Kasplex",
            "visit": "https://www.coingecko.com/en/coins/kroak-on-kaspa"
        },
        {
            "name": "BOMO",
            "symbol": "BOMO",
            "price": 4.2931e-08,
            "tvl": 12308.91,
            "volume_24h": 79602,
            "change_24h": -0.09006,
            "category": "KRC-20",
            "network": "Kasplex",
            "visit": "https://www.coingecko.com/en/coins/bomo"
        },
        {
            "name": "SZAR",
            "symbol": "SZAR",
            "price": 6.6893e-08,
            "tvl": 6330.3,
            "volume_24h": 46462,
            "change_24h": -5.76594,
            "category": "KRC-20",
            "network": "Kasplex",
            "visit": "https://www.coingecko.com/en/coins/szar"
        },
        {
            "name": "Froppy",
            "symbol": "FROPPY",
            "price": 5.998e-09,
            "tvl": 1721.39,
            "volume_24h": 7.25,
            "change_24h": 0,
            "category": "KRC-20",
            "network": "Kasplex",
            "visit": "https://www.coingecko.com/en/coins/froppy"
        }
    ]
}